rl_autoscale/__init__.py
rl_autoscale/fastapi_middleware.py
rl_autoscale/flask_middleware.py
rl_autoscale/metrics.py
rl_autoscale/py.typed
rl_autoscale-1.0.4.dist-info/licenses/LICENSE
rl_autoscale-1.0.4.dist-info/METADATA
rl_autoscale-1.0.4.dist-info/WHEEL
rl_autoscale-1.0.4.dist-info/top_level.txt
rl_autoscale-1.0.4.dist-info/RECORD
