Metadata-Version: 2.4
Name: rl-autoscale
Version: 1.0.4
Summary: Production-ready metrics instrumentation for RL-based autoscaling systems
Author-email: Fauzan Ghaza Madani <contact@fauzanghaza.com>
Project-URL: Homepage, https://github.com/ghazafm/rl-autoscale
Project-URL: Documentation, https://github.com/ghazafm/rl-autoscale#readme
Project-URL: Repository, https://github.com/ghazafm/rl-autoscale
Project-URL: Issues, https://github.com/ghazafm/rl-autoscale/issues
Project-URL: Changelog, https://github.com/ghazafm/rl-autoscale/blob/main/CHANGELOG.md
Keywords: reinforcement-learning,autoscaling,kubernetes,prometheus,observability,metrics,rl,dqn,q-learning
Classifier: Development Status :: 4 - Beta
Classifier: Intended Audience :: Developers
Classifier: Topic :: System :: Monitoring
Classifier: Programming Language :: Python :: 3
Classifier: Programming Language :: Python :: 3.10
Classifier: Programming Language :: Python :: 3.11
Classifier: Programming Language :: Python :: 3.12
Requires-Python: >=3.10
License-File: LICENSE
Requires-Dist: prometheus-client>=0.19.0
Provides-Extra: flask
Requires-Dist: flask>=2.0.0; extra == "flask"
Provides-Extra: fastapi
Requires-Dist: fastapi>=0.100.0; extra == "fastapi"
Requires-Dist: starlette>=0.27.0; extra == "fastapi"
Requires-Dist: uvicorn>=0.38.0; extra == "fastapi"
Provides-Extra: dev
Requires-Dist: pytest>=7.0.0; extra == "dev"
Requires-Dist: pytest-cov>=4.0.0; extra == "dev"
Requires-Dist: ruff>=0.8.0; extra == "dev"
Requires-Dist: build>=1.0.0; extra == "dev"
Requires-Dist: twine>=5.0.0; extra == "dev"
Dynamic: license-file
